cadquery_ocp_novtk/LICENSE
cadquery_ocp_novtk-7.8.1.1.post1.dist-info/DELVEWHEEL
cadquery_ocp_novtk-7.8.1.1.post1.dist-info/METADATA
cadquery_ocp_novtk-7.8.1.1.post1.dist-info/RECORD
cadquery_ocp_novtk-7.8.1.1.post1.dist-info/top_level.txt
cadquery_ocp_novtk-7.8.1.1.post1.dist-info/WHEEL
cadquery_ocp_novtk.libs/deflate-96db6a49d758b48d8fae423c78320d3d.dll
cadquery_ocp_novtk.libs/FreeImage-9f61ce1b33ff0dc3a56ac49dd2046f3f.dll
cadquery_ocp_novtk.libs/freetype-ebe27f2eb7393aa8371408242f1f70ea.dll
cadquery_ocp_novtk.libs/Iex-e85df212035357aa16f743bec0172786.dll
cadquery_ocp_novtk.libs/IlmThread-f0513a1a556d15c9f0180a06ee71776f.dll
cadquery_ocp_novtk.libs/Imath-68fd819ee4a09cf514344bcb3f237c81.dll
cadquery_ocp_novtk.libs/jpeg8-f224769b4eba73591642e676c230c22c.dll
cadquery_ocp_novtk.libs/lcms2-63950a68b9f0eeaa6b3ce398eb971a28.dll
cadquery_ocp_novtk.libs/Lerc-e1127ce80322af59ef148e36c1046cf8.dll
cadquery_ocp_novtk.libs/liblzma-463a42e93de461eb2a588e1b3ca1d5ce.dll
cadquery_ocp_novtk.libs/libpng16-31cee8076f8ffb2ab1fc7f01c4e67503.dll
cadquery_ocp_novtk.libs/libsharpyuv-e24fae5825b5eb36163620d0c7bc8a13.dll
cadquery_ocp_novtk.libs/libwebp-72779f08f45d397714825c3bd7c188a9.dll
cadquery_ocp_novtk.libs/libwebpmux-664108d4e0375c7917501bf340fd4810.dll
cadquery_ocp_novtk.libs/msvcp140-118148827badc04c45fc246c97d50bbe.dll
cadquery_ocp_novtk.libs/OpenEXR-e4599e8e66c42f3d44bd5ac7c6a8cfca.dll
cadquery_ocp_novtk.libs/OpenEXRCore-fc5a2e4c89c4bb6aaa0829d88b9219d7.dll
cadquery_ocp_novtk.libs/openjp2-43c2d5844adc1f5c6574b21ab609ff7d.dll
cadquery_ocp_novtk.libs/raw-5ecff5788e985d0b1f5fec62936e2e27.dll
cadquery_ocp_novtk.libs/tiff-8bc32bd300988fdb1201c2b0b3fa9d88.dll
cadquery_ocp_novtk.libs/TKBin-40245aeb6d34b87b66d3ee42e6f3c2d1.dll
cadquery_ocp_novtk.libs/TKBinL-8ae34eeedc653788e04dd0ae7f8a0005.dll
cadquery_ocp_novtk.libs/TKBinTObj-13766d3f7056c5d3e7f79b1d85d3ccc5.dll
cadquery_ocp_novtk.libs/TKBinXCAF-44b51fa90722461ff15dfd32c90268cb.dll
cadquery_ocp_novtk.libs/TKBO-afb14e653eba42f464d4e187dbe98124.dll
cadquery_ocp_novtk.libs/TKBool-ce2926098f7dd23bf957751321610692.dll
cadquery_ocp_novtk.libs/TKBRep-2644c4fad56da5151045ccffc2e35990.dll
cadquery_ocp_novtk.libs/TKCAF-da761d3681dd459e3ecc526c5325cd9d.dll
